client/__init__.py
client/api_client.py
client/api_response.py
client/configuration.py
client/exceptions.py
client/rest.py
client/api/__init__.py
client/api/alert_api.py
client/api/endpoint_api.py
client/api/environment_api.py
client/api/log_api.py
client/api/model_endpoints_api.py
client/api/model_schema_api.py
client/api/models_api.py
client/api/prediction_jobs_api.py
client/api/project_api.py
client/api/secret_api.py
client/api/standard_transformer_api.py
client/api/version_api.py
client/api/version_image_api.py
client/models/__init__.py
client/models/alert_condition_metric_type.py
client/models/alert_condition_severity.py
client/models/autoscaling_policy.py
client/models/binary_classification_output.py
client/models/build_image_options.py
client/models/config.py
client/models/container.py
client/models/custom_predictor.py
client/models/deployment_mode.py
client/models/endpoint_status.py
client/models/env_var.py
client/models/environment.py
client/models/file_format.py
client/models/gpu_config.py
client/models/gpu_toleration.py
client/models/ground_truth_job.py
client/models/ground_truth_source.py
client/models/image_building_job_state.py
client/models/image_building_job_status.py
client/models/label.py
client/models/list_jobs_paginated_response.py
client/models/logger.py
client/models/logger_config.py
client/models/logger_mode.py
client/models/metrics_type.py
client/models/mock_response.py
client/models/model.py
client/models/model_endpoint.py
client/models/model_endpoint_alert.py
client/models/model_endpoint_alert_condition.py
client/models/model_endpoint_rule.py
client/models/model_endpoint_rule_destination.py
client/models/model_observability.py
client/models/model_prediction_config.py
client/models/model_prediction_output.py
client/models/model_prediction_output_class.py
client/models/model_schema.py
client/models/mounted_mlp_secret.py
client/models/operation_tracing.py
client/models/paging.py
client/models/pipeline_tracing.py
merlin_sdk-0.49.4.dist-info/METADATA
merlin_sdk-0.49.4.dist-info/WHEEL
merlin_sdk-0.49.4.dist-info/entry_points.txt
merlin_sdk-0.49.4.dist-info/top_level.txt
merlin_sdk-0.49.4.dist-info/zip-safe
merlin_sdk-0.49.4.dist-info/RECORD
