Metadata-Version: 2.1
Name: merlin-sdk
Version: 0.49.4
Summary: Python SDK for Merlin
Home-page: https://github.com/caraml-dev/merlin
Author: Merlin
Requires-Python: >=3.9,<3.14
Requires-Dist: boto3>=1.35.39
Requires-Dist: caraml-upi-protos>=0.3.1
Requires-Dist: certifi>=2017.4.17
Requires-Dist: Click<8.1.4,>=7.0
Requires-Dist: cloudpickle==2.0.0
Requires-Dist: cookiecutter>=1.7.2
Requires-Dist: dataclasses-json>=0.5.2
Requires-Dist: docker<=6.1.3
Requires-Dist: GitPython>=3.1.40
Requires-Dist: google-cloud-storage>=1.19.0
Requires-Dist: protobuf<5,>=4.21.6
Requires-Dist: mlflow==1.26.1
Requires-Dist: PyPrind>=2.11.2
Requires-Dist: python-dateutil>=2.5.3
Requires-Dist: PyYAML>=5.4
Requires-Dist: six>=1.10
Requires-Dist: urllib3>=1.26
Requires-Dist: numpy>=1.26.4
Requires-Dist: caraml-auth-google==0.0.0.post9
Requires-Dist: pydantic==2.5.3
Requires-Dist: grpcio-tools<1.63,>=1.50.0
Requires-Dist: grpcio>=1.60.1
Provides-Extra: test
Requires-Dist: google-cloud-bigquery-storage>=0.7.0; extra == "test"
Requires-Dist: google-cloud-bigquery>=1.18.0; extra == "test"
Requires-Dist: joblib<1.2.0,>=0.13.0; extra == "test"
Requires-Dist: mypy>=0.812; extra == "test"
Requires-Dist: pytest-cov; extra == "test"
Requires-Dist: pytest-dependency; extra == "test"
Requires-Dist: pytest-xdist; extra == "test"
Requires-Dist: pytest; extra == "test"
Requires-Dist: recursive-diff>=1.0.0; extra == "test"
Requires-Dist: requests; extra == "test"
Requires-Dist: scikit-learn>=1.1.2; extra == "test"
Requires-Dist: types-python-dateutil; extra == "test"
Requires-Dist: types-PyYAML; extra == "test"
Requires-Dist: types-six; extra == "test"
Requires-Dist: types-protobuf; extra == "test"
Requires-Dist: urllib3-mock>=0.3.3; extra == "test"
Requires-Dist: xarray; extra == "test"
Requires-Dist: xgboost==1.6.2; extra == "test"
